harlequin_nebulagraph/__init__.py
harlequin_nebulagraph/adapter.py
harlequin_nebulagraph/cli_options.py
harlequin_nebulagraph/keywords.py
harlequin_nebulagraph/py.typed
harlequin_nebulagraph-0.4.1.dist-info/LICENSE
harlequin_nebulagraph-0.4.1.dist-info/METADATA
harlequin_nebulagraph-0.4.1.dist-info/WHEEL
harlequin_nebulagraph-0.4.1.dist-info/entry_points.txt
harlequin_nebulagraph-0.4.1.dist-info/RECORD
