Metadata-Version: 2.3
Name: harlequin-nebulagraph
Version: 0.4.1
Summary: A Harlequin adapter for NebulaGraph.
License: Apache-2.0
Author: Wey Gu
Author-email: weyl.gu@gmail.com
Requires-Python: >=3.8.1,<4.0
Classifier: License :: OSI Approved :: Apache Software License
Classifier: Programming Language :: Python :: 3
Classifier: Programming Language :: Python :: 3.9
Classifier: Programming Language :: Python :: 3.10
Classifier: Programming Language :: Python :: 3.11
Classifier: Programming Language :: Python :: 3.12
Classifier: Programming Language :: Python :: 3.13
Requires-Dist: harlequin (>=1.7,<3)
Requires-Dist: nebula3-python (>=3.8.0,<4.0.0)
